LICENSE
MANIFEST.in
README.md
setup.cfg
setup.py
versioneer.py
./.gitattributes
./CODE_OF_CONDUCT.md
./CONTRIBUTING.md
./LICENSE
./MANIFEST.in
./README.md
./requirements.txt
./setup.cfg
./setup.py
./versioneer.py
./adadjust/__init__.py
./adadjust/_version.py
./adadjust/functions.py
./adadjust.egg-info/PKG-INFO
./adadjust.egg-info/SOURCES.txt
./adadjust.egg-info/dependency_links.txt
./adadjust.egg-info/requires.txt
./adadjust.egg-info/top_level.txt
./tests/__init__.py
./tests/test_adadjust.py
./tests/data/plot.png
./tests/data/table.pdf
./tests/data/table.tex
adadjust/__init__.py
adadjust/_version.py
adadjust/functions.py
adadjust.egg-info/PKG-INFO
adadjust.egg-info/SOURCES.txt
adadjust.egg-info/dependency_links.txt
adadjust.egg-info/requires.txt
adadjust.egg-info/top_level.txt
tests/__init__.py
tests/test_adadjust.py