Metadata-Version: 2.1
Name: adadjust
Version: 0.1.46
Summary: A package to fit functions on data
Home-page: https://github.com/Advestis/adadjust
Author: Advestis
Author-email: pythondev@advestis.com
License: GPLv3
Project-URL: Bug Tracker, https://github.com/Advestis/adadjust/issues
Project-URL: Documentation, https://advestis.github.io/adadjust
Project-URL: Source Code, https://github.com/Advestis/adadjust/
Platform: UNKNOWN
Classifier: Development Status :: 5 - Production/Stable
Classifier: License :: OSI Approved :: GNU General Public License v3 (GPLv3)
Classifier: Operating System :: Unix
Classifier: Programming Language :: Python :: 3.7
Classifier: Programming Language :: Python :: 3.8
Classifier: Programming Language :: Python :: 3.9
Requires-Python: >=3.7
License-File: LICENSE
